{
  "status_code": 200,
  "status_message": "",
  "data": {
    "title": "สายกิจการ สาขา",
    "subTitle": "สาขา ย่อย",
    "items": [
      {"name": "สายกิจการ สาขา 1", "amt": "11 สาขา"},
      {"name": "สายกิจการ สาขา 2", "amt": "22 สาขา"},
      {"name": "สายกิจการ สาขา 3", "amt": "33 สาขา"},
      {"name": "สายกิจการ สาขา 4", "amt": "44 สาขา"},
      {"name": "สายกิจการ สาขา 5", "amt": "55 สาขา"},
      {"name": "สายกิจการ สาขา 6", "amt": "66 สาขา"},
      {"name": "สายกิจการ สาขา 7", "amt": "77 สาขา"},
      {"name": "สายกิจการ สาขา 8", "amt": "88 สาขา"},
      {"name": "สายกิจการ สาขา 9", "amt": "99 สาขา"}
      ]
  }
}
